{
    "z0u1y0": {
        "00": 0.041,
        "01": 0.048,
        "10": 0.242,
        "11": 0.227
    },
    "z0u1y1": {
        "00": 0.064,
        "01": 0.052,
        "10": 0.167,
        "11": 0.159
    },
    "z0u2y0": {
        "00": 0.076,
        "01": 0.076,
        "10": 0.339,
        "11": 0.303
    },
    "z0u2y1": {
        "00": 0.03,
        "01": 0.03,
        "10": 0.076,
        "11": 0.07
    },
    "z0u3y0": {
        "00": 0.081,
        "01": 0.075,
        "10": 0.324,
        "11": 0.348
    },
    "z0u3y1": {
        "00": 0.023,
        "01": 0.016,
        "10": 0.069,
        "11": 0.064
    },
    "z1y0": {
        "00": 0.047,
        "01": 0.066,
        "10": 0.249,
        "11": 0.244
    },
    "z1y1": {
        "00": 0.042,
        "01": 0.049,
        "10": 0.163,
        "11": 0.14
    }
}