{
    "z0u1y1": {
        "00": 0.1264,
        "10": 0.1251,
        "11": 0.1236,
        "01": 0.1284
    },
    "z0u3y1": {
        "10": 0.2488,
        "01": 0.2504
    },
    "z0u1y0": {
        "00": 0.1199,
        "10": 0.123,
        "11": 0.1263,
        "01": 0.1273
    },
    "z0u3y0": {
        "00": 0.2514,
        "11": 0.2494
    },
    "z1y0": {
        "00": 0.1245,
        "10": 0.1222,
        "11": 0.1273,
        "01": 0.1264
    },
    "z0u2y0": {
        "00": 0.1222,
        "10": 0.1243,
        "11": 0.1224,
        "01": 0.126
    },
    "z0u2y1": {
        "00": 0.1271,
        "10": 0.1234,
        "11": 0.1284,
        "01": 0.1262
    },
    "z1y1": {
        "00": 0.1237,
        "10": 0.1249,
        "11": 0.1248,
        "01": 0.1262
    }
}
