{
    "z0u1y1": {
        "10": 0.252,
        "11": 0.2423
    },
    "z0u3y1": {
        "00": 0.1233,
        "10": 0.1275,
        "11": 0.1212,
        "01": 0.1244
    },
    "z0u1y0": {
        "00": 0.2477,
        "01": 0.258
    },
    "z0u3y0": {
        "00": 0.1191,
        "10": 0.1294,
        "11": 0.1259,
        "01": 0.1292
    },
    "z1y0": {
        "00": 0.2462,
        "01": 0.2552
    },
    "z0u2y0": {
        "00": 0.1301,
        "10": 0.1234,
        "11": 0.1244,
        "01": 0.1267
    },
    "z0u2y1": {
        "00": 0.1279,
        "10": 0.1201,
        "11": 0.126,
        "01": 0.1214
    },
    "z1y1": {
        "10": 0.245,
        "11": 0.2536
    }
}
