{
    "z0u1y1": {
        "111": 0.5088,
        "110": 0.4912
    },
    "z0u3y1": {
        "000": 0.2515,
        "111": 0.2485,
        "001": 0.2436,
        "110": 0.2564
    },
    "z0u1y0": {
        "000": 0.4978,
        "001": 0.5022
    },
    "z0u3y0": {
        "000": 0.2574,
        "111": 0.2425,
        "001": 0.2501,
        "110": 0.25
    },
    "z1y0": {
        "000": 0.2528,
        "111": 0.2497,
        "001": 0.2472,
        "110": 0.2503
    },
    "z0u2y0": {
        "000": 0.2467,
        "111": 0.2569,
        "001": 0.2483,
        "110": 0.2481
    },
    "z0u2y1": {
        "000": 0.2487,
        "111": 0.2416,
        "001": 0.2566,
        "110": 0.2531
    },
    "z1y1": {
        "000": 0.2528,
        "111": 0.2497,
        "001": 0.2472,
        "110": 0.2503
    }
}
