{
    "z0u1y0": {
        "000": 0.167,
        "001": 0.06,
        "010": 0.123,
        "011": 0.123,
        "100": 0.176,
        "101": 0.1,
        "110": 0.113,
        "111": 0.138
    },
    "z0u1y1": {
        "000": 0.183,
        "001": 0.09,
        "010": 0.1,
        "011": 0.136,
        "100": 0.148,
        "101": 0.1,
        "110": 0.102,
        "111": 0.141
    },
    "z0u2y0": {
        "000": 0.04,
        "001": 0.014,
        "010": 0.01,
        "011": 0.017,
        "100": 0.283,
        "101": 0.184,
        "110": 0.179,
        "111": 0.273
    },
    "z0u2y1": {
        "000": 0.346,
        "001": 0.151,
        "010": 0.198,
        "011": 0.239,
        "100": 0.028,
        "101": 0.015,
        "110": 0.013,
        "111": 0.01
    },
    "z0u3y0": {
        "000": 0.266,
        "001": 0.094,
        "010": 0.094,
        "011": 0.079,
        "100": 0.113,
        "101": 0.079,
        "110": 0.113,
        "111": 0.162
    },
    "z0u3y1": {
        "000": 0.125,
        "001": 0.048,
        "010": 0.119,
        "011": 0.16,
        "100": 0.188,
        "101": 0.127,
        "110": 0.117,
        "111": 0.116
    },
    "z1y0": {
        "000": 0.178,
        "001": 0.0815,
        "010": 0.119,
        "011": 0.1255,
        "100": 0.147,
        "101": 0.0825,
        "110": 0.1255,
        "111": 0.141
    },
    "z1y1": {
        "000": 0.178,
        "001": 0.0815,
        "010": 0.119,
        "011": 0.1255,
        "100": 0.147,
        "101": 0.0825,
        "110": 0.1255,
        "111": 0.141
    }
}