{
    "z0u1y1": {
        "111": 0.493,
        "110": 0.507
    },
    "z0u3y1": {
        "000": 0.2505,
        "111": 0.2535,
        "001": 0.2423,
        "110": 0.2537
    },
    "z0u1y0": {
        "000": 0.509,
        "001": 0.491
    },
    "z0u3y0": {
        "000": 0.2465,
        "111": 0.2548,
        "001": 0.2478,
        "110": 0.2509
    },
    "z1y0": {
        "000": 0.2473,
        "111": 0.2463,
        "001": 0.2527,
        "110": 0.2537
    },
    "z0u2y0": {
        "000": 0.2566,
        "111": 0.2585,
        "001": 0.2412,
        "110": 0.2437
    },
    "z0u2y1": {
        "000": 0.2563,
        "111": 0.2446,
        "001": 0.2474,
        "110": 0.2517
    },
    "z1y1": {
        "000": 0.2473,
        "111": 0.2463,
        "001": 0.2527,
        "110": 0.2537
    }
}
