{
    "z0u1y0": {
        "000": 0.091,
        "001": 0.13,
        "010": 0.161,
        "011": 0.148,
        "100": 0.082,
        "101": 0.109,
        "110": 0.149,
        "111": 0.13
    },
    "z0u1y1": {
        "000": 0.095,
        "001": 0.129,
        "010": 0.142,
        "011": 0.089,
        "100": 0.105,
        "101": 0.143,
        "110": 0.173,
        "111": 0.124
    },
    "z0u2y0": {
        "000": 0.078,
        "001": 0.112,
        "010": 0.196,
        "011": 0.142,
        "100": 0.102,
        "101": 0.141,
        "110": 0.136,
        "111": 0.093
    },
    "z0u2y1": {
        "000": 0.104,
        "001": 0.145,
        "010": 0.163,
        "011": 0.113,
        "100": 0.066,
        "101": 0.083,
        "110": 0.193,
        "111": 0.133
    },
    "z0u3y0": {
        "000": 0.014,
        "001": 0.022,
        "010": 0.026,
        "011": 0.013,
        "100": 0.138,
        "101": 0.196,
        "110": 0.345,
        "111": 0.246
    },
    "z0u3y1": {
        "000": 0.187,
        "001": 0.203,
        "010": 0.327,
        "011": 0.215,
        "100": 0.015,
        "101": 0.023,
        "110": 0.019,
        "111": 0.011
    },
    "z1y0": {
        "000": 0.094,
        "001": 0.1235,
        "010": 0.167,
        "011": 0.1075,
        "100": 0.081,
        "101": 0.1255,
        "110": 0.1805,
        "111": 0.121
    },
    "z1y1": {
        "000": 0.094,
        "001": 0.1235,
        "010": 0.167,
        "011": 0.1075,
        "100": 0.081,
        "101": 0.1255,
        "110": 0.1805,
        "111": 0.121
    }
}