{
    "z0u1y0": {
        "000": 0.14,
        "001": 0.154,
        "010": 0.137,
        "011": 0.088,
        "100": 0.123,
        "101": 0.109,
        "110": 0.146,
        "111": 0.103
    },
    "z0u1y1": {
        "000": 0.099,
        "001": 0.112,
        "010": 0.139,
        "011": 0.146,
        "100": 0.097,
        "101": 0.101,
        "110": 0.152,
        "111": 0.154
    },
    "z0u2y0": {
        "000": 0.133,
        "001": 0.122,
        "010": 0.204,
        "011": 0.119,
        "100": 0.105,
        "101": 0.104,
        "110": 0.122,
        "111": 0.091
    },
    "z0u2y1": {
        "000": 0.093,
        "001": 0.105,
        "010": 0.093,
        "011": 0.09,
        "100": 0.103,
        "101": 0.137,
        "110": 0.204,
        "111": 0.175
    },
    "z0u3y0": {
        "000": 0.013,
        "001": 0.018,
        "010": 0.023,
        "011": 0.017,
        "100": 0.204,
        "101": 0.222,
        "110": 0.279,
        "111": 0.224
    },
    "z0u3y1": {
        "000": 0.214,
        "001": 0.242,
        "010": 0.253,
        "011": 0.224,
        "100": 0.016,
        "101": 0.011,
        "110": 0.021,
        "111": 0.019
    },
    "z1y0": {
        "000": 0.1035,
        "001": 0.135,
        "010": 0.1335,
        "011": 0.1375,
        "100": 0.099,
        "101": 0.115,
        "110": 0.1485,
        "111": 0.128
    },
    "z1y1": {
        "000": 0.1035,
        "001": 0.135,
        "010": 0.1335,
        "011": 0.1375,
        "100": 0.099,
        "101": 0.115,
        "110": 0.1485,
        "111": 0.128
    }
}