{
    "z0u1y0": {
        "000": 0.144,
        "001": 0.135,
        "010": 0.136,
        "011": 0.117,
        "100": 0.111,
        "101": 0.12,
        "110": 0.122,
        "111": 0.115
    },
    "z0u1y1": {
        "000": 0.144,
        "001": 0.117,
        "010": 0.107,
        "011": 0.113,
        "100": 0.171,
        "101": 0.115,
        "110": 0.138,
        "111": 0.095
    },
    "z0u2y0": {
        "000": 0.138,
        "001": 0.154,
        "010": 0.157,
        "011": 0.177,
        "100": 0.105,
        "101": 0.097,
        "110": 0.084,
        "111": 0.088
    },
    "z0u2y1": {
        "000": 0.117,
        "001": 0.121,
        "010": 0.093,
        "011": 0.092,
        "100": 0.147,
        "101": 0.129,
        "110": 0.16,
        "111": 0.141
    },
    "z0u3y0": {
        "000": 0.023,
        "001": 0.014,
        "010": 0.013,
        "011": 0.015,
        "100": 0.242,
        "101": 0.225,
        "110": 0.224,
        "111": 0.244
    },
    "z0u3y1": {
        "000": 0.267,
        "001": 0.225,
        "010": 0.222,
        "011": 0.209,
        "100": 0.025,
        "101": 0.022,
        "110": 0.013,
        "111": 0.017
    },
    "z1y0": {
        "000": 0.1215,
        "001": 0.1315,
        "010": 0.126,
        "011": 0.122,
        "100": 0.1275,
        "101": 0.1335,
        "110": 0.127,
        "111": 0.111
    },
    "z1y1": {
        "000": 0.1215,
        "001": 0.1315,
        "010": 0.126,
        "011": 0.122,
        "100": 0.1275,
        "101": 0.1335,
        "110": 0.127,
        "111": 0.111
    }
}