{
    "z0u1y0": {
        "00": 0.188,
        "01": 0.028,
        "10": 0.255,
        "11": 0.027
    },
    "z0u1y1": {
        "00": 0.207,
        "01": 0.022,
        "10": 0.225,
        "11": 0.048
    },
    "z0u2y0": {
        "00": 0.193,
        "01": 0.017,
        "10": 0.262,
        "11": 0.028
    },
    "z0u2y1": {
        "00": 0.221,
        "01": 0.034,
        "10": 0.209,
        "11": 0.036
    },
    "z0u3y0": {
        "00": 0.035,
        "01": 0.021,
        "10": 0.018,
        "11": 0.018
    },
    "z0u3y1": {
        "00": 0.382,
        "01": 0.035,
        "10": 0.44,
        "11": 0.051
    },
    "z1y0": {
        "00": 0.22,
        "01": 0.028,
        "10": 0.297,
        "11": 0.04
    },
    "z1y1": {
        "00": 0.164,
        "01": 0.021,
        "10": 0.195,
        "11": 0.035
    }
}