{
    "z0u1y0": {
        "000": 0.049,
        "001": 0.013,
        "010": 0.216,
        "011": 0.246,
        "100": 0.042,
        "101": 0.029,
        "110": 0.211,
        "111": 0.194
    },
    "z0u1y1": {
        "000": 0.031,
        "001": 0.057,
        "010": 0.235,
        "011": 0.183,
        "100": 0.037,
        "101": 0.045,
        "110": 0.231,
        "111": 0.181
    },
    "z0u2y0": {
        "000": 0.051,
        "001": 0.053,
        "010": 0.277,
        "011": 0.19,
        "100": 0.048,
        "101": 0.03,
        "110": 0.191,
        "111": 0.16
    },
    "z0u2y1": {
        "000": 0.043,
        "001": 0.052,
        "010": 0.199,
        "011": 0.188,
        "100": 0.055,
        "101": 0.032,
        "110": 0.236,
        "111": 0.195
    },
    "z0u3y0": {
        "000": 0.029,
        "001": 0.029,
        "010": 0.046,
        "011": 0.035,
        "100": 0.043,
        "101": 0.058,
        "110": 0.415,
        "111": 0.345
    },
    "z0u3y1": {
        "000": 0.059,
        "001": 0.058,
        "010": 0.423,
        "011": 0.374,
        "100": 0.025,
        "101": 0.02,
        "110": 0.024,
        "111": 0.017
    },
    "z1y0": {
        "000": 0.0435,
        "001": 0.057,
        "010": 0.2645,
        "011": 0.1675,
        "100": 0.032,
        "101": 0.0365,
        "110": 0.216,
        "111": 0.183
    },
    "z1y1": {
        "000": 0.0435,
        "001": 0.057,
        "010": 0.2645,
        "011": 0.1675,
        "100": 0.032,
        "101": 0.0365,
        "110": 0.216,
        "111": 0.183
    }
}